{"cameraMode":{"drawMode":0,"name":"Shaded","section":"Shading Mode"},"sceneLighting":true,"audioPlay":false,"sceneViewState":{"m_AlwaysRefresh":false,"showFog":true,"showSkybox":true,"showFlares":true,"showImageEffects":true,"showParticleSystems":true,"showVisualEffectGraphs":true,"m_FxEnabled":true},"in2DMode":false,"pivot":{"x":125.49212646484375,"y":17.424396514892579,"z":-3.131235122680664},"rotation":{"x":0.008690036833286286,"y":0.009596480056643486,"z":0.00008231677202275023,"w":-0.9999064207077026},"size":10.0,"orthographic":false}